ripiu/djangocms_aoxomoxoa/__init__.py
ripiu/djangocms_aoxomoxoa/apps.py
ripiu/djangocms_aoxomoxoa/cms_plugins.py
ripiu/djangocms_aoxomoxoa/conf.py
ripiu/djangocms_aoxomoxoa/admin/__init__.py
ripiu/djangocms_aoxomoxoa/admin/base.py
ripiu/djangocms_aoxomoxoa/admin/__pycache__/__init__.cpython-36.pyc
ripiu/djangocms_aoxomoxoa/admin/options/__init__.py
ripiu/djangocms_aoxomoxoa/admin/options/carousel.py
ripiu/djangocms_aoxomoxoa/admin/options/gallery.py
ripiu/djangocms_aoxomoxoa/admin/options/grid_panel.py
ripiu/djangocms_aoxomoxoa/admin/options/lightbox.py
ripiu/djangocms_aoxomoxoa/admin/options/lightbox_text_panel.py
ripiu/djangocms_aoxomoxoa/admin/options/main.py
ripiu/djangocms_aoxomoxoa/admin/options/navigation.py
ripiu/djangocms_aoxomoxoa/admin/options/slider.py
ripiu/djangocms_aoxomoxoa/admin/options/strip_panel.py
ripiu/djangocms_aoxomoxoa/admin/options/theme.py
ripiu/djangocms_aoxomoxoa/admin/options/thumbnail.py
ripiu/djangocms_aoxomoxoa/admin/options/tile_design.py
ripiu/djangocms_aoxomoxoa/admin/options/tile_text_panel.py
ripiu/djangocms_aoxomoxoa/admin/options/tiles.py
ripiu/djangocms_aoxomoxoa/admin/options/__pycache__/__init__.cpython-36.pyc
ripiu/djangocms_aoxomoxoa/admin/options/__pycache__/carousel.cpython-36.pyc
ripiu/djangocms_aoxomoxoa/admin/options/__pycache__/gallery.cpython-36.pyc
ripiu/djangocms_aoxomoxoa/admin/options/__pycache__/grid_panel.cpython-36.pyc
ripiu/djangocms_aoxomoxoa/admin/options/__pycache__/lightbox.cpython-36.pyc
ripiu/djangocms_aoxomoxoa/admin/options/__pycache__/lightbox_text_panel.cpython-36.pyc
ripiu/djangocms_aoxomoxoa/admin/options/__pycache__/main.cpython-36.pyc
ripiu/djangocms_aoxomoxoa/admin/options/__pycache__/navigation.cpython-36.pyc
ripiu/djangocms_aoxomoxoa/admin/options/__pycache__/slider.cpython-36.pyc
ripiu/djangocms_aoxomoxoa/admin/options/__pycache__/strip_panel.cpython-36.pyc
ripiu/djangocms_aoxomoxoa/admin/options/__pycache__/theme.cpython-36.pyc
ripiu.djangocms_aoxomoxoa-0.0.4.dist-info/LICENSE.txt
ripiu.djangocms_aoxomoxoa-0.0.4.dist-info/METADATA
ripiu.djangocms_aoxomoxoa-0.0.4.dist-info/RECORD
ripiu.djangocms_aoxomoxoa-0.0.4.dist-info/WHEEL
ripiu.djangocms_aoxomoxoa-0.0.4.dist-info/top_level.txt
