Metadata-Version: 2.1
Name: ripiu.djangocms-aoxomoxoa
Version: 0.0.4
Summary: Unite gallery on django cms
Home-page: https://github.com/ripiu/djangocms_aoxomoxoa
Author: matteo vezzola
Author-email: matteo@studioripiu.it
License: BSD-new
Platform: UNKNOWN
Classifier: Development Status :: 3 - Alpha
Classifier: Framework :: Django
Classifier: Intended Audience :: Developers
Classifier: License :: OSI Approved :: BSD License
Classifier: Operating System :: OS Independent
Classifier: Programming Language :: Python
Classifier: Topic :: Internet :: WWW/HTTP :: Dynamic Content
Requires-Python: >=3.3
Requires-Dist: Django (>=1.8)
Requires-Dist: django-cms (>=3.1)
Requires-Dist: django-appconf
